solvien_graph/__init__.py
solvien_graph/bioinformatics.py
solvien_graph/core.py
solvien_graph/styles.py
solvien_graph/biograph/__init__.py
solvien_graph/biograph/charts.py
solvien_graph-0.1.4.dist-info/METADATA
solvien_graph-0.1.4.dist-info/WHEEL
solvien_graph-0.1.4.dist-info/top_level.txt
solvien_graph-0.1.4.dist-info/RECORD
