Metadata-Version: 2.4
Name: solvien-graph
Version: 0.1.4
Summary: Professional data visualization library - Optimized for bioinformatics and scientific analyses (D3.js/Vega-Lite/Altair based)
Home-page: https://github.com/Solvien-Open-Source/solvien-graph
Author: Yasin Polat
Classifier: Development Status :: 3 - Alpha
Classifier: Intended Audience :: Science/Research
Classifier: Topic :: Scientific/Engineering :: Visualization
Classifier: License :: OSI Approved :: MIT License
Classifier: Programming Language :: Python :: 3
Classifier: Programming Language :: Python :: 3.8
Classifier: Programming Language :: Python :: 3.9
Classifier: Programming Language :: Python :: 3.10
Classifier: Programming Language :: Python :: 3.11
Classifier: Programming Language :: Python :: 3.12
Requires-Python: >=3.8
Requires-Dist: altair>=5.0.0
Requires-Dist: pandas>=1.0.0
Requires-Dist: numpy>=1.20.0
Dynamic: author
Dynamic: classifier
Dynamic: description
Dynamic: description-content-type
Dynamic: home-page
Dynamic: requires-dist
Dynamic: requires-python
Dynamic: summary
